corasa/__init__.py
corasa/actions/__init__.py
corasa/actions/core.py
corasa/actions/default_functions.py
corasa/actions/helpers.py
corasa/actions/patch_action_executor.py
corasa/actions/util.py
corasa/api/__init__.py
corasa/api/__main__.py
corasa/api/api.py
corasa/api/models.py
corasa/api/rasa_api.py
corasa/api/twilio_api.py
corasa/api/utils.py
corasa/components/__init__.py
corasa/components/datetime_util.py
corasa/components/duckling_entity_extractor.py
corasa/components/monkey_patching.py
corasa-0.1.17.dist-info/LICENSE
corasa-0.1.17.dist-info/WHEEL
corasa-0.1.17.dist-info/METADATA
corasa-0.1.17.dist-info/RECORD
