Metadata-Version: 2.1
Name: corasa
Version: 0.1.17
Summary: Components for running a RASA project exported from Colang.
Author: Razvan Dinu
Author-email: drazvan@gmail.com
Requires-Python: >=3.8,<4.0
Classifier: Programming Language :: Python :: 3
Classifier: Programming Language :: Python :: 3.8
Requires-Dist: aiohttp (==3.8.1)
Requires-Dist: fastapi (>=0.79.0,<0.80.0)
Requires-Dist: pydantic (==1.9.1)
Requires-Dist: python-dateutil (==2.8.1)
Requires-Dist: python-multipart (==0.0.5)
Requires-Dist: requests (>=2.24.0,<3.0.0)
Requires-Dist: starlette (==0.19.1)
Requires-Dist: twilio (==6.50.1)
Requires-Dist: uvicorn (==0.18.2)
